LICENSE.txt
MANIFEST.in
README.txt
build.txt
distribute_setup.py
narc_testrunfinished.py
setup.py
narc_testrun_finished.egg-info/PKG-INFO
narc_testrun_finished.egg-info/SOURCES.txt
narc_testrun_finished.egg-info/dependency_links.txt
narc_testrun_finished.egg-info/entry_points.txt
narc_testrun_finished.egg-info/requires.txt
narc_testrun_finished.egg-info/top_level.txt