Metadata-Version: 1.0
Name: narc-testrun-finished
Version: 1.0.6
Summary: A plugin for narc to mark testruns as finished whenever they run out of NO_RESULT results
Home-page: http://code.google.com/p/slickqa
Author: Slick Developers
Author-email: UNKNOWN
License: License :: OSI Approved :: Apache Software License
Platform: UNKNOWN
